README.md
setup.py
fastapi_ratelimit/__init__.py
fastapi_ratelimit/errors.py
fastapi_ratelimit/limiter.py
fastapi_ratelimit/middleware.py
fastapi_ratelimit/wrappers.py
fastapi_ratelimit.egg-info/PKG-INFO
fastapi_ratelimit.egg-info/SOURCES.txt
fastapi_ratelimit.egg-info/dependency_links.txt
fastapi_ratelimit.egg-info/requires.txt
fastapi_ratelimit.egg-info/top_level.txt