Metadata-Version: 2.1
Name: fastapi-ratelimit
Version: 0.0.5
Summary: API Rate limit
Home-page: UNKNOWN
Author: gin
Author-email: vothien1632@gmail.com
License: UNKNOWN
Keywords: fastapi-ratelimit
Platform: UNKNOWN
Classifier: Development Status :: 1 - Planning
Classifier: Intended Audience :: Developers
Classifier: Programming Language :: Python :: 3
Classifier: Operating System :: Unix
Classifier: Operating System :: MacOS :: MacOS X
Classifier: Operating System :: Microsoft :: Windows
